{
  "code": 200,
  "msg": "操作成功",
  "data": [
    {
      "stageCode": "1-7",
      "zoneName": "第一章",
      "orundumPerAp": 1.0899173562176399,
      "stageEfficiency": 0.9999999422441888,
      "orundumPerApEfficiency": 0.9999241800161833,
      "stageType": "MAIN",
      "lmdcost": 9.535958133055075
    },
    {
      "stageCode": "CW-6",
      "zoneName": "孤星·插曲",
      "orundumPerAp": 0.9068886677038837,
      "stageEfficiency": 0.9744136789620478,
      "orundumPerApEfficiency": 0.8320079520219116,
      "stageType": "ACT_PERM",
      "lmdcost": 6.469299421130861
    },
    {
      "stageCode": "S2-12",
      "zoneName": "第二章",
      "orundumPerAp": 0.8634094589911819,
      "stageEfficiency": 0.7522402616982848,
      "orundumPerApEfficiency": 0.7921187697166806,
      "stageType": "MAIN",
      "lmdcost": 9.283919798223925
    },
    {
      "stageCode": "DV-5",
      "zoneName": "绿野幻梦·别传",
      "orundumPerAp": 0.8588537029971597,
      "stageEfficiency": 0.7485624112931534,
      "orundumPerApEfficiency": 0.7879391770616143,
      "stageType": "ACT_PERM",
      "lmdcost": 9.276063081517314
    },
    {
      "stageCode": "DM-5",
      "zoneName": "生于黑夜·插曲",
      "orundumPerAp": 0.8567378154928194,
      "stageEfficiency": 0.747124991227024,
      "orundumPerApEfficiency": 0.7859979958649719,
      "stageType": "ACT_PERM",
      "lmdcost": 9.282819876645949
    },
    {
      "stageCode": "TW-1",
      "zoneName": "沃伦姆德的薄暮·别传",
      "orundumPerAp": 0.7660994327660995,
      "stageEfficiency": 0.7173483780678522,
      "orundumPerApEfficiency": 0.7028435162991737,
      "stageType": "ACT_PERM",
      "lmdcost": 9.468292682926826
    },
    {
      "stageCode": "DH-1",
      "zoneName": "多索雷斯假日·别传",
      "orundumPerAp": 0.7600837138508373,
      "stageEfficiency": 0.7219840664092742,
      "orundumPerApEfficiency": 0.6973245081200341,
      "stageType": "ACT_PERM",
      "lmdcost": 9.485857321652063
    },
    {
      "stageCode": "GT-1",
      "zoneName": "骑兵与猎人·别传",
      "orundumPerAp": 0.7358420544793289,
      "stageEfficiency": 0.6948231059296529,
      "orundumPerApEfficiency": 0.6750844536507604,
      "stageType": "ACT_PERM",
      "lmdcost": 9.527375428686709
    },
    {
      "stageCode": "IW-1",
      "zoneName": "将进酒·别传",
      "orundumPerAp": 0.7336648875950185,
      "stageEfficiency": 0.630359461621149,
      "orundumPerApEfficiency": 0.6730870528394665,
      "stageType": "ACT_PERM",
      "lmdcost": 9.528575365114357
    },
    {
      "stageCode": "TW-5",
      "zoneName": "沃伦姆德的薄暮·别传",
      "orundumPerAp": 0.732023860357388,
      "stageEfficiency": 0.794237114135765,
      "orundumPerApEfficiency": 0.6715815232636586,
      "stageType": "ACT_PERM",
      "lmdcost": 6.457850918282571
    },
    {
      "stageCode": "CW-2",
      "zoneName": "孤星·插曲",
      "orundumPerAp": 0.7292202227934875,
      "stageEfficiency": 0.6287515733443447,
      "orundumPerApEfficiency": 0.6690093787096215,
      "stageType": "ACT_PERM",
      "lmdcost": 9.527301214257735
    },
    {
      "stageCode": "S3-4",
      "zoneName": "第三章",
      "orundumPerAp": 0.7253704353474568,
      "stageEfficiency": 0.7880086704134008,
      "orundumPerApEfficiency": 0.6654774636215199,
      "stageType": "MAIN",
      "lmdcost": 6.46956856975036
    },
    {
      "stageCode": "MN-2",
      "zoneName": "玛莉娅·临光·别传",
      "orundumPerAp": 0.7142258274120188,
      "stageEfficiency": 0.6490619677351624,
      "orundumPerApEfficiency": 0.6552530526715769,
      "stageType": "ACT_PERM",
      "lmdcost": 9.564079236977255
    },
    {
      "stageCode": "NL-7",
      "zoneName": "长夜临光·别传",
      "orundumPerAp": 0.6940089925871916,
      "stageEfficiency": 0.7439641399068168,
      "orundumPerApEfficiency": 0.6367054977864143,
      "stageType": "ACT_PERM",
      "lmdcost": 9.599999999999998
    },
    {
      "stageCode": "BI-1",
      "zoneName": "风雪过境·别传",
      "orundumPerAp": 0.60121062891146,
      "stageEfficiency": 0.6751092315788374,
      "orundumPerApEfficiency": 0.5515693843224404,
      "stageType": "ACT_PERM",
      "lmdcost": 6.144368600682594
    },
    {
      "stageCode": "1-12",
      "zoneName": "第一章",
      "orundumPerAp": 0.5978934935128606,
      "stageEfficiency": 0.7318142669317166,
      "orundumPerApEfficiency": 0.5485261408374867,
      "stageType": "MAIN",
      "lmdcost": 6.147002981288296
    },
    {
      "stageCode": "GA-1",
      "zoneName": "吾导先路·别传",
      "orundumPerAp": 0.5936332245399935,
      "stageEfficiency": 0.6589905250019661,
      "orundumPerApEfficiency": 0.5446176371926545,
      "stageType": "ACT_PERM",
      "lmdcost": 6.174980079681275
    },
    {
      "stageCode": "S2-5",
      "zoneName": "第二章",
      "orundumPerAp": 0.585421198382123,
      "stageEfficiency": 0.5803458625645317,
      "orundumPerApEfficiency": 0.5370836682404798,
      "stageType": "MAIN",
      "lmdcost": 9.265322415175989
    },
    {
      "stageCode": "NL-2",
      "zoneName": "长夜临光·别传",
      "orundumPerAp": 0.5844108408210972,
      "stageEfficiency": 0.664747488577055,
      "orundumPerApEfficiency": 0.5361567346982542,
      "stageType": "ACT_PERM",
      "lmdcost": 6.13725
    },
    {
      "stageCode": "S3-7",
      "zoneName": "第三章",
      "orundumPerAp": 0.5689943066368923,
      "stageEfficiency": 0.760053278781018,
      "orundumPerApEfficiency": 0.522013125354947,
      "stageType": "MAIN",
      "lmdcost": 9.599999999999998
    },
    {
      "stageCode": "SN-7",
      "zoneName": "愚人号·插曲",
      "orundumPerAp": 0.5681492109038737,
      "stageEfficiency": 0.7920470096167925,
      "orundumPerApEfficiency": 0.5212378081686915,
      "stageType": "ACT_PERM",
      "lmdcost": 5.999999999999998
    },
    {
      "stageCode": "DH-6",
      "zoneName": "多索雷斯假日·别传",
      "orundumPerAp": 0.5662994217846539,
      "stageEfficiency": 0.6622088106078219,
      "orundumPerApEfficiency": 0.5195407539308751,
      "stageType": "ACT_PERM",
      "lmdcost": 6.699137633666781
    },
    {
      "stageCode": "14-11",
      "zoneName": "第十四章(标准)",
      "orundumPerAp": 0.5558925781630321,
      "stageEfficiency": 0.838252344559294,
      "orundumPerApEfficiency": 0.5099931909752587,
      "stageType": "MAIN",
      "lmdcost": 6.000000000000001
    },
    {
      "stageCode": "GT-3",
      "zoneName": "骑兵与猎人·别传",
      "orundumPerAp": 0.5441267627460097,
      "stageEfficiency": 0.5467419195282449,
      "orundumPerApEfficiency": 0.49919886490459603,
      "stageType": "ACT_PERM",
      "lmdcost": 9.2001423994304
    },
    {
      "stageCode": "9-3",
      "zoneName": "第九章",
      "orundumPerAp": 0.530641247368915,
      "stageEfficiency": 0.5468705207663788,
      "orundumPerApEfficiency": 0.48682683244854585,
      "stageType": "MAIN",
      "lmdcost": 5.999999999999999
    },
    {
      "stageCode": "GA-4",
      "zoneName": "吾导先路·别传",
      "orundumPerAp": 0.4943382873319179,
      "stageEfficiency": 0.555595496997115,
      "orundumPerApEfficiency": 0.4535213645246953,
      "stageType": "ACT_PERM",
      "lmdcost": 6.490909090909091
    },
    {
      "stageCode": "2-3",
      "zoneName": "第二章",
      "orundumPerAp": 0.4909242688276653,
      "stageEfficiency": 0.600809776353907,
      "orundumPerApEfficiency": 0.45038923745657367,
      "stageType": "MAIN",
      "lmdcost": 6.497238832379068
    },
    {
      "stageCode": "0-9",
      "zoneName": "序章",
      "orundumPerAp": 0.4755259247501003,
      "stageEfficiency": 0.5143109145088502,
      "orundumPerApEfficiency": 0.43626231628449563,
      "stageType": "MAIN",
      "lmdcost": 9.560109416291901
    },
    {
      "stageCode": "S5-1",
      "zoneName": "第五章",
      "orundumPerAp": 0.46326309082162836,
      "stageEfficiency": 0.4978485253403858,
      "orundumPerApEfficiency": 0.4250120099280994,
      "stageType": "MAIN",
      "lmdcost": 9.6
    },
    {
      "stageCode": "S6-2",
      "zoneName": "第六章",
      "orundumPerAp": 0.4616968715115319,
      "stageEfficiency": 0.37013944511099495,
      "orundumPerApEfficiency": 0.4235751114784696,
      "stageType": "MAIN",
      "lmdcost": 9.599999999999998
    },
    {
      "stageCode": "5-10",
      "zoneName": "第五章",
      "orundumPerAp": 0.4401122883495002,
      "stageEfficiency": 0.9283328675926372,
      "orundumPerApEfficiency": 0.40377274160504606,
      "stageType": "MAIN",
      "lmdcost": 9.600000000000001
    },
    {
      "stageCode": "14-20",
      "zoneName": "第十四章(标准)",
      "orundumPerAp": 0.3878289931764378,
      "stageEfficiency": 0.9714265933371317,
      "orundumPerApEfficiency": 0.3558064157581998,
      "stageType": "MAIN",
      "lmdcost": 9.6
    },
    {
      "stageCode": "1-5",
      "zoneName": "第一章",
      "orundumPerAp": 0.38408404356592984,
      "stageEfficiency": 0.5380356016123492,
      "orundumPerApEfficiency": 0.3523706821705778,
      "stageType": "MAIN",
      "lmdcost": 6.067904643878257
    },
    {
      "stageCode": "S5-5",
      "zoneName": "第五章",
      "orundumPerAp": 0.3796740959651931,
      "stageEfficiency": 0.4035765266731038,
      "orundumPerApEfficiency": 0.34832485868366336,
      "stageType": "MAIN",
      "lmdcost": 6.000000000000001
    },
    {
      "stageCode": "M8-6",
      "zoneName": "第八章",
      "orundumPerAp": 0.37110276184826313,
      "stageEfficiency": 0.5220408449111933,
      "orundumPerApEfficiency": 0.3404612494020762,
      "stageType": "MAIN",
      "lmdcost": 6.0
    },
    {
      "stageCode": "DV-4",
      "zoneName": "绿野幻梦·别传",
      "orundumPerAp": 0.3698501872659176,
      "stageEfficiency": 0.5447139912937079,
      "orundumPerApEfficiency": 0.3393120984090987,
      "stageType": "ACT_PERM",
      "lmdcost": 5.999999999999999
    },
    {
      "stageCode": "MB-4",
      "zoneName": "孤岛风云·别传",
      "orundumPerAp": 0.36835748792270534,
      "stageEfficiency": 0.5515820733175489,
      "orundumPerApEfficiency": 0.33794264947037184,
      "stageType": "ACT_PERM",
      "lmdcost": 5.999999999999998
    },
    {
      "stageCode": "6-11",
      "zoneName": "第六章",
      "orundumPerAp": 0.3572854091949307,
      "stageEfficiency": 0.4250906924661375,
      "orundumPerApEfficiency": 0.32778477907791803,
      "stageType": "MAIN",
      "lmdcost": 6.000000000000001
    },
    {
      "stageCode": "7-16",
      "zoneName": "第七章",
      "orundumPerAp": 0.2842836190301586,
      "stageEfficiency": 0.9467406881184092,
      "orundumPerApEfficiency": 0.26081065966069594,
      "stageType": "MAIN",
      "lmdcost": 9.600000000000001
    },
    {
      "stageCode": "R8-6",
      "zoneName": "第八章",
      "orundumPerAp": 0.2419783931339209,
      "stageEfficiency": 0.6621169374036465,
      "orundumPerApEfficiency": 0.22199852581093657,
      "stageType": "MAIN",
      "lmdcost": 7.81376673040153
    },
    {
      "stageCode": "R8-1",
      "zoneName": "第八章",
      "orundumPerAp": 0.23554469711207165,
      "stageEfficiency": 0.30114503409502547,
      "orundumPerApEfficiency": 0.216096052396396,
      "stageType": "MAIN",
      "lmdcost": 7.980851063829787
    },
    {
      "stageCode": "7-13",
      "zoneName": "第七章",
      "orundumPerAp": 0.23221220092696981,
      "stageEfficiency": 0.6504225309130336,
      "orundumPerApEfficiency": 0.21303871644676128,
      "stageType": "MAIN",
      "lmdcost": 8.012407282535401
    },
    {
      "stageCode": "5-9",
      "zoneName": "第五章",
      "orundumPerAp": 0.23216765415208362,
      "stageEfficiency": 0.7576738658369734,
      "orundumPerApEfficiency": 0.21299784784594827,
      "stageType": "MAIN",
      "lmdcost": 7.973581032802858
    },
    {
      "stageCode": "4-3",
      "zoneName": "第四章",
      "orundumPerAp": 0.23098655880587124,
      "stageEfficiency": 0.6489117071739342,
      "orundumPerApEfficiency": 0.2119142741338268,
      "stageType": "MAIN",
      "lmdcost": 8.009702130043273
    },
    {
      "stageCode": "4-1",
      "zoneName": "第四章",
      "orundumPerAp": 0.22991277690367376,
      "stageEfficiency": 0.3022725616699661,
      "orundumPerApEfficiency": 0.21092915312263646,
      "stageType": "MAIN",
      "lmdcost": 7.969557690349299
    },
    {
      "stageCode": "S4-10",
      "zoneName": "第四章",
      "orundumPerAp": 0.22967073131546817,
      "stageEfficiency": 0.7539642113123343,
      "orundumPerApEfficiency": 0.21070709294997078,
      "stageType": "MAIN",
      "lmdcost": 7.999519083635726
    },
    {
      "stageCode": "6-14",
      "zoneName": "第六章",
      "orundumPerAp": 0.22616792729553273,
      "stageEfficiency": 0.7546468002330494,
      "orundumPerApEfficiency": 0.20749351128030524,
      "stageType": "MAIN",
      "lmdcost": 8.007709524993786
    },
    {
      "stageCode": "5-2",
      "zoneName": "第五章",
      "orundumPerAp": 0.22459139668043773,
      "stageEfficiency": 0.8945945304550603,
      "orundumPerApEfficiency": 0.20604715291783277,
      "stageType": "MAIN",
      "lmdcost": 7.998773674337927
    },
    {
      "stageCode": "9-9",
      "zoneName": "第九章",
      "orundumPerAp": 0.22435689955456914,
      "stageEfficiency": 0.46137835653657855,
      "orundumPerApEfficiency": 0.20583201793997166,
      "stageType": "MAIN",
      "lmdcost": 7.997911585889464
    },
    {
      "stageCode": "5-1",
      "zoneName": "第五章",
      "orundumPerAp": 0.2241681436741062,
      "stageEfficiency": 0.6992624646010014,
      "orundumPerApEfficiency": 0.20565884740743687,
      "stageType": "MAIN",
      "lmdcost": 8.014457060610907
    },
    {
      "stageCode": "S5-8",
      "zoneName": "第五章",
      "orundumPerAp": 0.22375705596092813,
      "stageEfficiency": 0.949493240978717,
      "orundumPerApEfficiency": 0.2052817027164478,
      "stageType": "MAIN",
      "lmdcost": 8.008408492228249
    },
    {
      "stageCode": "9-13",
      "zoneName": "第九章",
      "orundumPerAp": 0.2214670030824653,
      "stageEfficiency": 0.868631596159407,
      "orundumPerApEfficiency": 0.20318073677290394,
      "stageType": "MAIN",
      "lmdcost": 8.017747891497606
    },
    {
      "stageCode": "9-4",
      "zoneName": "第九章",
      "orundumPerAp": 0.22056538484369162,
      "stageEfficiency": 0.9654292387547486,
      "orundumPerApEfficiency": 0.2023535640767813,
      "stageType": "MAIN",
      "lmdcost": 8.029888787746863
    },
    {
      "stageCode": "6-3",
      "zoneName": "第六章",
      "orundumPerAp": 0.22039823214319862,
      "stageEfficiency": 0.7253826310589748,
      "orundumPerApEfficiency": 0.20220021297541158,
      "stageType": "MAIN",
      "lmdcost": 7.997347751320702
    },
    {
      "stageCode": "10-4",
      "zoneName": "第十章 (标准)",
      "orundumPerAp": 0.22004505982457293,
      "stageEfficiency": 0.9851139591688878,
      "orundumPerApEfficiency": 0.2018762016739201,
      "stageType": "MAIN",
      "lmdcost": 6.0
    },
    {
      "stageCode": "5-5",
      "zoneName": "第五章",
      "orundumPerAp": 0.21933626640545126,
      "stageEfficiency": 0.9342085202631536,
      "orundumPerApEfficiency": 0.20122593248206536,
      "stageType": "MAIN",
      "lmdcost": 8.01400340997003
    },
    {
      "stageCode": "9-17",
      "zoneName": "第九章",
      "orundumPerAp": 0.21768304905678035,
      "stageEfficiency": 0.9308198715188536,
      "orundumPerApEfficiency": 0.19970921931814709,
      "stageType": "MAIN",
      "lmdcost": 8.012422906412965
    },
    {
      "stageCode": "4-4",
      "zoneName": "第四章",
      "orundumPerAp": 0.21750004829786357,
      "stageEfficiency": 0.4749658609535664,
      "orundumPerApEfficiency": 0.19954132871363628,
      "stageType": "MAIN",
      "lmdcost": 8.00854762341714
    },
    {
      "stageCode": "M8-8",
      "zoneName": "第八章",
      "orundumPerAp": 0.2172648152941966,
      "stageEfficiency": 0.989176704872895,
      "orundumPerApEfficiency": 0.19932551861852899,
      "stageType": "MAIN",
      "lmdcost": 7.995178928497552
    },
    {
      "stageCode": "S7-1",
      "zoneName": "第七章",
      "orundumPerAp": 0.21708044298405746,
      "stageEfficiency": 0.3217487792821955,
      "orundumPerApEfficiency": 0.19915636971014444,
      "stageType": "MAIN",
      "lmdcost": 7.97028731604765
    },
    {
      "stageCode": "4-7",
      "zoneName": "第四章",
      "orundumPerAp": 0.21689364359012944,
      "stageEfficiency": 0.9251158885312338,
      "orundumPerApEfficiency": 0.1989849941193848,
      "stageType": "MAIN",
      "lmdcost": 8.012190279119658
    },
    {
      "stageCode": "4-6",
      "zoneName": "第四章",
      "orundumPerAp": 0.21591624011827448,
      "stageEfficiency": 0.8872042301257148,
      "orundumPerApEfficiency": 0.19808829368649034,
      "stageType": "MAIN",
      "lmdcost": 8.00573377559512
    },
    {
      "stageCode": "S9-2",
      "zoneName": "第九章",
      "orundumPerAp": 0.20861332949239916,
      "stageEfficiency": 0.7343508508643497,
      "orundumPerApEfficiency": 0.19138837568110015,
      "stageType": "MAIN",
      "lmdcost": 8.008957509779167
    },
    {
      "stageCode": "MB-7",
      "zoneName": "孤岛风云·别传",
      "orundumPerAp": 0.20788610062427518,
      "stageEfficiency": 0.8707910188280926,
      "orundumPerApEfficiency": 0.19072119323327996,
      "stageType": "ACT_PERM",
      "lmdcost": 8.063857566765579
    },
    {
      "stageCode": "RI-9",
      "zoneName": "密林悍将归来·别传",
      "orundumPerAp": 0.20711001866266102,
      "stageEfficiency": 0.8295077995944364,
      "orundumPerApEfficiency": 0.19000919143363396,
      "stageType": "ACT_PERM",
      "lmdcost": 7.9569230769230765
    },
    {
      "stageCode": "SV-8",
      "zoneName": "覆潮之下·插曲",
      "orundumPerAp": 0.20710112980786718,
      "stageEfficiency": 0.7842111021535181,
      "orundumPerApEfficiency": 0.19000103652097905,
      "stageType": "ACT_PERM",
      "lmdcost": 7.990796522350049
    },
    {
      "stageCode": "IW-6",
      "zoneName": "将进酒·别传",
      "orundumPerAp": 0.20599172448589387,
      "stageEfficiency": 0.8679415658200997,
      "orundumPerApEfficiency": 0.18898323347329712,
      "stageType": "ACT_PERM",
      "lmdcost": 8.002077297962426
    },
    {
      "stageCode": "BI-8",
      "zoneName": "风雪过境·别传",
      "orundumPerAp": 0.20547755367083997,
      "stageEfficiency": 0.8972262790490954,
      "orundumPerApEfficiency": 0.18851151712921096,
      "stageType": "ACT_PERM",
      "lmdcost": 7.97429424800077
    },
    {
      "stageCode": "WD-8",
      "zoneName": "遗尘漫步·插曲",
      "orundumPerAp": 0.20520776862260004,
      "stageEfficiency": 0.9621350315706461,
      "orundumPerApEfficiency": 0.1882640079106422,
      "stageType": "ACT_PERM",
      "lmdcost": 8.0049236158412
    },
    {
      "stageCode": "TW-8",
      "zoneName": "沃伦姆德的薄暮·别传",
      "orundumPerAp": 0.2049724966391633,
      "stageEfficiency": 0.8881371300439549,
      "orundumPerApEfficiency": 0.18804816205427824,
      "stageType": "ACT_PERM",
      "lmdcost": 7.990553194689933
    },
    {
      "stageCode": "NL-9",
      "zoneName": "长夜临光·别传",
      "orundumPerAp": 0.20229885057471264,
      "stageEfficiency": 0.7729469625518851,
      "orundumPerApEfficiency": 0.18559527575661708,
      "stageType": "ACT_PERM",
      "lmdcost": 8.163636363636364
    },
    {
      "stageCode": "WR-10",
      "zoneName": "画中人·别传",
      "orundumPerAp": 0.20134861916505586,
      "stageEfficiency": 0.8337550066793686,
      "orundumPerApEfficiency": 0.18472350382115216,
      "stageType": "ACT_PERM",
      "lmdcost": 8.017655172413793
    },
    {
      "stageCode": "DH-7",
      "zoneName": "多索雷斯假日·别传",
      "orundumPerAp": 0.200540507339844,
      "stageEfficiency": 0.7938821901663258,
      "orundumPerApEfficiency": 0.18398211682554494,
      "stageType": "ACT_PERM",
      "lmdcost": 8.131699846860643
    }
  ]
}