{
  "code": 200,
  "msg": "操作成功",
  "data": [
    {
      "stageCode": "1-7",
      "zoneName": "第一章",
      "orundumPerAp": 1.0899189892016794,
      "stageEfficiency": 1.0000000381675853,
      "orundumPerApEfficiency": 0.9999256781666783,
      "stageType": "MAIN",
      "lmdcost": 9.535961730528474
    },
    {
      "stageCode": "AD-3",
      "zoneName": "红丝绒",
      "orundumPerAp": 0.9747947687420316,
      "stageEfficiency": 0.8725273483206729,
      "orundumPerApEfficiency": 0.8943071272862675,
      "stageType": "ACT",
      "lmdcost": 8.572728942092025
    },
    {
      "stageCode": "CW-6",
      "zoneName": "孤星·插曲",
      "orundumPerAp": 0.9069048068161648,
      "stageEfficiency": 0.9744318445716954,
      "orundumPerApEfficiency": 0.8320227585469401,
      "stageType": "ACT_PERM",
      "lmdcost": 6.469295695664313
    },
    {
      "stageCode": "S2-12",
      "zoneName": "第二章",
      "orundumPerAp": 0.8634164319488854,
      "stageEfficiency": 0.7522369289251655,
      "orundumPerApEfficiency": 0.7921251669255829,
      "stageType": "MAIN",
      "lmdcost": 9.283929517425674
    },
    {
      "stageCode": "DV-5",
      "zoneName": "绿野幻梦·别传",
      "orundumPerAp": 0.8588537029971597,
      "stageEfficiency": 0.7485474099336394,
      "orundumPerApEfficiency": 0.7879391770616143,
      "stageType": "ACT_PERM",
      "lmdcost": 9.276063081517314
    },
    {
      "stageCode": "DM-5",
      "zoneName": "生于黑夜·插曲",
      "orundumPerAp": 0.8566771035236818,
      "stageEfficiency": 0.7470536762056991,
      "orundumPerApEfficiency": 0.7859422968107171,
      "stageType": "ACT_PERM",
      "lmdcost": 9.282909057155456
    },
    {
      "stageCode": "TW-1",
      "zoneName": "沃伦姆德的薄暮·别传",
      "orundumPerAp": 0.7660994327660995,
      "stageEfficiency": 0.7173593919443113,
      "orundumPerApEfficiency": 0.7028435162991737,
      "stageType": "ACT_PERM",
      "lmdcost": 9.468292682926826
    },
    {
      "stageCode": "DH-1",
      "zoneName": "多索雷斯假日·别传",
      "orundumPerAp": 0.7600837138508373,
      "stageEfficiency": 0.7219936194229146,
      "orundumPerApEfficiency": 0.6973245081200341,
      "stageType": "ACT_PERM",
      "lmdcost": 9.485857321652063
    },
    {
      "stageCode": "GT-1",
      "zoneName": "骑兵与猎人·别传",
      "orundumPerAp": 0.7358420544793289,
      "stageEfficiency": 0.694825178734799,
      "orundumPerApEfficiency": 0.6750844536507604,
      "stageType": "ACT_PERM",
      "lmdcost": 9.527375428686709
    },
    {
      "stageCode": "IW-1",
      "zoneName": "将进酒·别传",
      "orundumPerAp": 0.7336648875950185,
      "stageEfficiency": 0.6303612624430266,
      "orundumPerApEfficiency": 0.6730870528394665,
      "stageType": "ACT_PERM",
      "lmdcost": 9.528575365114357
    },
    {
      "stageCode": "TW-5",
      "zoneName": "沃伦姆德的薄暮·别传",
      "orundumPerAp": 0.732023860357388,
      "stageEfficiency": 0.7942390346482124,
      "orundumPerApEfficiency": 0.6715815232636586,
      "stageType": "ACT_PERM",
      "lmdcost": 6.457850918282571
    },
    {
      "stageCode": "CW-2",
      "zoneName": "孤星·插曲",
      "orundumPerAp": 0.7293196279980422,
      "stageEfficiency": 0.6289031935627601,
      "orundumPerApEfficiency": 0.6691005761449927,
      "stageType": "ACT_PERM",
      "lmdcost": 9.526587506453279
    },
    {
      "stageCode": "S3-4",
      "zoneName": "第三章",
      "orundumPerAp": 0.7253792183484005,
      "stageEfficiency": 0.7880445092273621,
      "orundumPerApEfficiency": 0.6654855214205508,
      "stageType": "MAIN",
      "lmdcost": 6.469495793499622
    },
    {
      "stageCode": "MN-2",
      "zoneName": "玛莉娅·临光·别传",
      "orundumPerAp": 0.7141516516516517,
      "stageEfficiency": 0.6488679245746106,
      "orundumPerApEfficiency": 0.6551850015152768,
      "stageType": "ACT_PERM",
      "lmdcost": 9.564257555847567
    },
    {
      "stageCode": "NL-7",
      "zoneName": "长夜临光·别传",
      "orundumPerAp": 0.6938993935069568,
      "stageEfficiency": 0.7438522979656857,
      "orundumPerApEfficiency": 0.63660494817152,
      "stageType": "ACT_PERM",
      "lmdcost": 9.6
    },
    {
      "stageCode": "BI-1",
      "zoneName": "风雪过境·别传",
      "orundumPerAp": 0.60121062891146,
      "stageEfficiency": 0.6751299257989031,
      "orundumPerApEfficiency": 0.5515693843224404,
      "stageType": "ACT_PERM",
      "lmdcost": 6.144368600682594
    },
    {
      "stageCode": "1-12",
      "zoneName": "第一章",
      "orundumPerAp": 0.5979075487402523,
      "stageEfficiency": 0.7318421096306311,
      "orundumPerApEfficiency": 0.5485390355415158,
      "stageType": "MAIN",
      "lmdcost": 6.1469693386357935
    },
    {
      "stageCode": "GA-1",
      "zoneName": "吾导先路·别传",
      "orundumPerAp": 0.5947116270499354,
      "stageEfficiency": 0.6598143877161152,
      "orundumPerApEfficiency": 0.5456069972935187,
      "stageType": "ACT_PERM",
      "lmdcost": 6.178466305189776
    },
    {
      "stageCode": "S2-5",
      "zoneName": "第二章",
      "orundumPerAp": 0.5854146470057996,
      "stageEfficiency": 0.5803799027251202,
      "orundumPerApEfficiency": 0.5370776578034858,
      "stageType": "MAIN",
      "lmdcost": 9.265316942966608
    },
    {
      "stageCode": "NL-2",
      "zoneName": "长夜临光·别传",
      "orundumPerAp": 0.5844108408210972,
      "stageEfficiency": 0.6647652091333417,
      "orundumPerApEfficiency": 0.5361567346982542,
      "stageType": "ACT_PERM",
      "lmdcost": 6.13725
    },
    {
      "stageCode": "S3-7",
      "zoneName": "第三章",
      "orundumPerAp": 0.5688289943605285,
      "stageEfficiency": 0.7601878123691628,
      "orundumPerApEfficiency": 0.5218614627160811,
      "stageType": "MAIN",
      "lmdcost": 9.6
    },
    {
      "stageCode": "AD-5",
      "zoneName": "红丝绒",
      "orundumPerAp": 0.5685744824152976,
      "stageEfficiency": 0.9246514220766259,
      "orundumPerApEfficiency": 0.5216279655186217,
      "stageType": "ACT",
      "lmdcost": 6.000000000000001
    },
    {
      "stageCode": "SN-7",
      "zoneName": "愚人号·插曲",
      "orundumPerAp": 0.5681492109038737,
      "stageEfficiency": 0.7921031659125917,
      "orundumPerApEfficiency": 0.5212378081686915,
      "stageType": "ACT_PERM",
      "lmdcost": 5.999999999999998
    },
    {
      "stageCode": "DH-6",
      "zoneName": "多索雷斯假日·别传",
      "orundumPerAp": 0.5673882681564245,
      "stageEfficiency": 0.6623386846578767,
      "orundumPerApEfficiency": 0.5205396955563527,
      "stageType": "ACT_PERM",
      "lmdcost": 6.70769230769231
    },
    {
      "stageCode": "14-11",
      "zoneName": "第十四章(标准)",
      "orundumPerAp": 0.5558486939044495,
      "stageEfficiency": 0.8377775353829636,
      "orundumPerApEfficiency": 0.5099529301875683,
      "stageType": "MAIN",
      "lmdcost": 6.0
    },
    {
      "stageCode": "GT-3",
      "zoneName": "骑兵与猎人·别传",
      "orundumPerAp": 0.5441267627460097,
      "stageEfficiency": 0.5467364803194977,
      "orundumPerApEfficiency": 0.49919886490459603,
      "stageType": "ACT_PERM",
      "lmdcost": 9.2001423994304
    },
    {
      "stageCode": "9-3",
      "zoneName": "第九章",
      "orundumPerAp": 0.5300592569147721,
      "stageEfficiency": 0.5463289241027832,
      "orundumPerApEfficiency": 0.48629289625208444,
      "stageType": "MAIN",
      "lmdcost": 6.0
    },
    {
      "stageCode": "GA-4",
      "zoneName": "吾导先路·别传",
      "orundumPerAp": 0.4943382873319179,
      "stageEfficiency": 0.5555983292160782,
      "orundumPerApEfficiency": 0.4535213645246953,
      "stageType": "ACT_PERM",
      "lmdcost": 6.490909090909091
    },
    {
      "stageCode": "2-3",
      "zoneName": "第二章",
      "orundumPerAp": 0.4909393573163958,
      "stageEfficiency": 0.6007544585558905,
      "orundumPerApEfficiency": 0.45040308010678515,
      "stageType": "MAIN",
      "lmdcost": 6.497377410667486
    },
    {
      "stageCode": "0-9",
      "zoneName": "序章",
      "orundumPerAp": 0.4754762554053528,
      "stageEfficiency": 0.5143036479968114,
      "orundumPerApEfficiency": 0.4362167480783053,
      "stageType": "MAIN",
      "lmdcost": 9.559852519459236
    },
    {
      "stageCode": "S5-1",
      "zoneName": "第五章",
      "orundumPerAp": 0.463234226248604,
      "stageEfficiency": 0.4978243850654005,
      "orundumPerApEfficiency": 0.424985528668444,
      "stageType": "MAIN",
      "lmdcost": 9.6
    },
    {
      "stageCode": "S6-2",
      "zoneName": "第六章",
      "orundumPerAp": 0.4616695195572633,
      "stageEfficiency": 0.37011638845990075,
      "orundumPerApEfficiency": 0.4235500179424434,
      "stageType": "MAIN",
      "lmdcost": 9.600000000000001
    },
    {
      "stageCode": "5-10",
      "zoneName": "第五章",
      "orundumPerAp": 0.4401122187191839,
      "stageEfficiency": 0.9282507303476034,
      "orundumPerApEfficiency": 0.40377267772402187,
      "stageType": "MAIN",
      "lmdcost": 9.6
    },
    {
      "stageCode": "14-20",
      "zoneName": "第十四章(标准)",
      "orundumPerAp": 0.38777319396481796,
      "stageEfficiency": 0.9713327155149782,
      "orundumPerApEfficiency": 0.3557552238209339,
      "stageType": "MAIN",
      "lmdcost": 9.6
    },
    {
      "stageCode": "1-5",
      "zoneName": "第一章",
      "orundumPerAp": 0.3838798661504066,
      "stageEfficiency": 0.5378784337230793,
      "orundumPerApEfficiency": 0.35218336344073997,
      "stageType": "MAIN",
      "lmdcost": 6.067719412975324
    },
    {
      "stageCode": "S5-5",
      "zoneName": "第五章",
      "orundumPerAp": 0.3796740959651931,
      "stageEfficiency": 0.40358427198598906,
      "orundumPerApEfficiency": 0.34832485868366336,
      "stageType": "MAIN",
      "lmdcost": 6.000000000000001
    },
    {
      "stageCode": "DV-4",
      "zoneName": "绿野幻梦·别传",
      "orundumPerAp": 0.3711170848267622,
      "stageEfficiency": 0.5458038759766572,
      "orundumPerApEfficiency": 0.3404743897493231,
      "stageType": "ACT_PERM",
      "lmdcost": 6.000000000000002
    },
    {
      "stageCode": "M8-6",
      "zoneName": "第八章",
      "orundumPerAp": 0.37099069512862615,
      "stageEfficiency": 0.5219420423419219,
      "orundumPerApEfficiency": 0.3403584358978221,
      "stageType": "MAIN",
      "lmdcost": 6.0
    },
    {
      "stageCode": "MB-4",
      "zoneName": "孤岛风云·别传",
      "orundumPerAp": 0.36864450657554104,
      "stageEfficiency": 0.5527556618978388,
      "orundumPerApEfficiency": 0.33820596933535874,
      "stageType": "ACT_PERM",
      "lmdcost": 6.000000000000001
    },
    {
      "stageCode": "6-11",
      "zoneName": "第六章",
      "orundumPerAp": 0.3572748574103777,
      "stageEfficiency": 0.42508762182401627,
      "orundumPerApEfficiency": 0.3277750985416309,
      "stageType": "MAIN",
      "lmdcost": 6.0
    },
    {
      "stageCode": "7-16",
      "zoneName": "第七章",
      "orundumPerAp": 0.28440528880458493,
      "stageEfficiency": 0.9465166599571889,
      "orundumPerApEfficiency": 0.26092228330695866,
      "stageType": "MAIN",
      "lmdcost": 9.6
    },
    {
      "stageCode": "R8-6",
      "zoneName": "第八章",
      "orundumPerAp": 0.24330777508743606,
      "stageEfficiency": 0.6606639543464723,
      "orundumPerApEfficiency": 0.22321814228205142,
      "stageType": "MAIN",
      "lmdcost": 7.813683483068419
    },
    {
      "stageCode": "AD-1",
      "zoneName": "红丝绒",
      "orundumPerAp": 0.2391546583470468,
      "stageEfficiency": 0.7021182063448661,
      "orundumPerApEfficiency": 0.2194079434376576,
      "stageType": "ACT",
      "lmdcost": 8.002647634396224
    },
    {
      "stageCode": "R8-1",
      "zoneName": "第八章",
      "orundumPerAp": 0.2356588504985224,
      "stageEfficiency": 0.30102736622999815,
      "orundumPerApEfficiency": 0.21620078027387374,
      "stageType": "MAIN",
      "lmdcost": 7.980369176677409
    },
    {
      "stageCode": "5-9",
      "zoneName": "第五章",
      "orundumPerAp": 0.23218396176110756,
      "stageEfficiency": 0.7577093792542364,
      "orundumPerApEfficiency": 0.21301280895514454,
      "stageType": "MAIN",
      "lmdcost": 7.9741545924884205
    },
    {
      "stageCode": "7-13",
      "zoneName": "第七章",
      "orundumPerAp": 0.2320492175564639,
      "stageEfficiency": 0.6505791627395856,
      "orundumPerApEfficiency": 0.21288919041877422,
      "stageType": "MAIN",
      "lmdcost": 8.012989323843415
    },
    {
      "stageCode": "4-3",
      "zoneName": "第四章",
      "orundumPerAp": 0.23114495269726248,
      "stageEfficiency": 0.6487652370425977,
      "orundumPerApEfficiency": 0.21205958963051602,
      "stageType": "MAIN",
      "lmdcost": 8.015947097002433
    },
    {
      "stageCode": "AD-2",
      "zoneName": "红丝绒",
      "orundumPerAp": 0.23044580752500654,
      "stageEfficiency": 0.6803707673695736,
      "orundumPerApEfficiency": 0.21141817204129038,
      "stageType": "ACT",
      "lmdcost": 7.988083070566487
    },
    {
      "stageCode": "4-1",
      "zoneName": "第四章",
      "orundumPerAp": 0.2301267503435073,
      "stageEfficiency": 0.30221393940071967,
      "orundumPerApEfficiency": 0.21112545903074062,
      "stageType": "MAIN",
      "lmdcost": 7.970508520059037
    },
    {
      "stageCode": "S4-10",
      "zoneName": "第四章",
      "orundumPerAp": 0.229894366815366,
      "stageEfficiency": 0.7540290619750609,
      "orundumPerApEfficiency": 0.2109122631333633,
      "stageType": "MAIN",
      "lmdcost": 7.998916449932639
    },
    {
      "stageCode": "6-14",
      "zoneName": "第六章",
      "orundumPerAp": 0.22613460506840355,
      "stageEfficiency": 0.754488297708529,
      "orundumPerApEfficiency": 0.20746294042972802,
      "stageType": "MAIN",
      "lmdcost": 8.008023349686393
    },
    {
      "stageCode": "5-2",
      "zoneName": "第五章",
      "orundumPerAp": 0.22459139668043773,
      "stageEfficiency": 0.8950409609097593,
      "orundumPerApEfficiency": 0.20604715291783277,
      "stageType": "MAIN",
      "lmdcost": 7.998773674337927
    },
    {
      "stageCode": "5-1",
      "zoneName": "第五章",
      "orundumPerAp": 0.22444313299520754,
      "stageEfficiency": 0.6997633642949012,
      "orundumPerApEfficiency": 0.2059111311882638,
      "stageType": "MAIN",
      "lmdcost": 8.01046681486186
    },
    {
      "stageCode": "9-9",
      "zoneName": "第九章",
      "orundumPerAp": 0.22441377500604778,
      "stageEfficiency": 0.4613717830281854,
      "orundumPerApEfficiency": 0.20588419725325482,
      "stageType": "MAIN",
      "lmdcost": 7.9967478189375605
    },
    {
      "stageCode": "S5-8",
      "zoneName": "第五章",
      "orundumPerAp": 0.22388919038254684,
      "stageEfficiency": 0.9496755578635658,
      "orundumPerApEfficiency": 0.20540292695646498,
      "stageType": "MAIN",
      "lmdcost": 8.008409858995856
    },
    {
      "stageCode": "9-13",
      "zoneName": "第九章",
      "orundumPerAp": 0.22152140990444474,
      "stageEfficiency": 0.8686778961648262,
      "orundumPerApEfficiency": 0.2032306512884814,
      "stageType": "MAIN",
      "lmdcost": 8.017478983954485
    },
    {
      "stageCode": "9-4",
      "zoneName": "第九章",
      "orundumPerAp": 0.22062781259554543,
      "stageEfficiency": 0.9651043325330924,
      "orundumPerApEfficiency": 0.20241083724361963,
      "stageType": "MAIN",
      "lmdcost": 8.029549616007799
    },
    {
      "stageCode": "6-3",
      "zoneName": "第六章",
      "orundumPerAp": 0.22050010839908862,
      "stageEfficiency": 0.7258104395487928,
      "orundumPerApEfficiency": 0.20229367743035653,
      "stageType": "MAIN",
      "lmdcost": 7.996846303682403
    },
    {
      "stageCode": "10-4",
      "zoneName": "第十章 (标准)",
      "orundumPerAp": 0.22007993246474175,
      "stageEfficiency": 0.9849895601394619,
      "orundumPerApEfficiency": 0.20190819492178141,
      "stageType": "MAIN",
      "lmdcost": 6.000000000000001
    },
    {
      "stageCode": "5-5",
      "zoneName": "第五章",
      "orundumPerAp": 0.2193416589120638,
      "stageEfficiency": 0.9341371799194875,
      "orundumPerApEfficiency": 0.20123087973583834,
      "stageType": "MAIN",
      "lmdcost": 8.014042514862185
    },
    {
      "stageCode": "9-17",
      "zoneName": "第九章",
      "orundumPerAp": 0.21774476559385034,
      "stageEfficiency": 0.9306099445599227,
      "orundumPerApEfficiency": 0.1997658399943581,
      "stageType": "MAIN",
      "lmdcost": 8.012298464520612
    },
    {
      "stageCode": "4-4",
      "zoneName": "第四章",
      "orundumPerAp": 0.21755561386127734,
      "stageEfficiency": 0.47504265420683367,
      "orundumPerApEfficiency": 0.19959230629474983,
      "stageType": "MAIN",
      "lmdcost": 8.008624448752519
    },
    {
      "stageCode": "M8-8",
      "zoneName": "第八章",
      "orundumPerAp": 0.21727252793863386,
      "stageEfficiency": 0.989219604211979,
      "orundumPerApEfficiency": 0.1993325944391136,
      "stageType": "MAIN",
      "lmdcost": 7.99520224997932
    },
    {
      "stageCode": "S7-1",
      "zoneName": "第七章",
      "orundumPerAp": 0.21702492683419114,
      "stageEfficiency": 0.3230865113428997,
      "orundumPerApEfficiency": 0.19910543746256065,
      "stageType": "MAIN",
      "lmdcost": 7.972843524761683
    },
    {
      "stageCode": "4-7",
      "zoneName": "第四章",
      "orundumPerAp": 0.2169301973185756,
      "stageEfficiency": 0.9250276635093475,
      "orundumPerApEfficiency": 0.19901852965006933,
      "stageType": "MAIN",
      "lmdcost": 8.012549067247756
    },
    {
      "stageCode": "4-6",
      "zoneName": "第四章",
      "orundumPerAp": 0.21598466877636918,
      "stageEfficiency": 0.8871552466942331,
      "orundumPerApEfficiency": 0.19815107227189832,
      "stageType": "MAIN",
      "lmdcost": 8.005565575480585
    },
    {
      "stageCode": "S9-2",
      "zoneName": "第九章",
      "orundumPerAp": 0.20867828748202788,
      "stageEfficiency": 0.7343169794197766,
      "orundumPerApEfficiency": 0.19144797016699805,
      "stageType": "MAIN",
      "lmdcost": 8.009309937267025
    },
    {
      "stageCode": "MB-7",
      "zoneName": "孤岛风云·别传",
      "orundumPerAp": 0.20788610062427518,
      "stageEfficiency": 0.8707681755869346,
      "orundumPerApEfficiency": 0.19072119323327996,
      "stageType": "ACT_PERM",
      "lmdcost": 8.063857566765579
    },
    {
      "stageCode": "SV-8",
      "zoneName": "覆潮之下·插曲",
      "orundumPerAp": 0.20710112980786718,
      "stageEfficiency": 0.7841973799981937,
      "orundumPerApEfficiency": 0.19000103652097905,
      "stageType": "ACT_PERM",
      "lmdcost": 7.990796522350049
    },
    {
      "stageCode": "RI-9",
      "zoneName": "密林悍将归来·别传",
      "orundumPerAp": 0.20665375549850623,
      "stageEfficiency": 0.8299538699439367,
      "orundumPerApEfficiency": 0.18959060137477635,
      "stageType": "ACT_PERM",
      "lmdcost": 7.9654195423174725
    },
    {
      "stageCode": "IW-6",
      "zoneName": "将进酒·别传",
      "orundumPerAp": 0.20598611041416262,
      "stageEfficiency": 0.8673160487961089,
      "orundumPerApEfficiency": 0.18897808294877302,
      "stageType": "ACT_PERM",
      "lmdcost": 8.001778740187929
    },
    {
      "stageCode": "BI-8",
      "zoneName": "风雪过境·别传",
      "orundumPerAp": 0.20547755367083997,
      "stageEfficiency": 0.8971962760629526,
      "orundumPerApEfficiency": 0.18851151712921096,
      "stageType": "ACT_PERM",
      "lmdcost": 7.97429424800077
    },
    {
      "stageCode": "WD-8",
      "zoneName": "遗尘漫步·插曲",
      "orundumPerAp": 0.20526355632452503,
      "stageEfficiency": 0.9622784221010028,
      "orundumPerApEfficiency": 0.18831518928855506,
      "stageType": "ACT_PERM",
      "lmdcost": 8.004590617379806
    },
    {
      "stageCode": "TW-8",
      "zoneName": "沃伦姆德的薄暮·别传",
      "orundumPerAp": 0.2049724966391633,
      "stageEfficiency": 0.8881084832325437,
      "orundumPerApEfficiency": 0.18804816205427824,
      "stageType": "ACT_PERM",
      "lmdcost": 7.990553194689933
    },
    {
      "stageCode": "NL-9",
      "zoneName": "长夜临光·别传",
      "orundumPerAp": 0.20229885057471264,
      "stageEfficiency": 0.7729337283961805,
      "orundumPerApEfficiency": 0.18559527575661708,
      "stageType": "ACT_PERM",
      "lmdcost": 8.163636363636364
    },
    {
      "stageCode": "WR-10",
      "zoneName": "画中人·别传",
      "orundumPerAp": 0.20134861916505586,
      "stageEfficiency": 0.8337488037180035,
      "orundumPerApEfficiency": 0.18472350382115216,
      "stageType": "ACT_PERM",
      "lmdcost": 8.017655172413793
    },
    {
      "stageCode": "DH-7",
      "zoneName": "多索雷斯假日·别传",
      "orundumPerAp": 0.200540507339844,
      "stageEfficiency": 0.7938760198047119,
      "orundumPerApEfficiency": 0.18398211682554494,
      "stageType": "ACT_PERM",
      "lmdcost": 8.131699846860643
    }
  ]
}